barbariantuw/__init__.py
barbariantuw/__main__.py
barbariantuw/ai.py
barbariantuw/anims.py
barbariantuw/core.py
barbariantuw/scenes.py
barbariantuw/sprites.py
barbariantuw/viewer.py
barbariantuw/fnt/OFL.txt
barbariantuw/fnt/PressStart2P-Regular.ttf
barbariantuw/img/menu/controls1.gif
barbariantuw/img/menu/controls2.gif
barbariantuw/img/menu/heroes.png
barbariantuw/img/menu/icone.gif
barbariantuw/img/menu/icone.ico
barbariantuw/img/menu/logoDS.png
barbariantuw/img/menu/menu.png
barbariantuw/img/menu/team.png
barbariantuw/img/menu/titre2.png
barbariantuw/img/menu/titreDS.png
barbariantuw/img/sprites/drax1.gif
barbariantuw/img/sprites/drax2.gif
barbariantuw/img/sprites/feu1.gif
barbariantuw/img/sprites/feu2.gif
barbariantuw/img/sprites/feu3.gif
barbariantuw/img/sprites/gicle1.gif
barbariantuw/img/sprites/gicle2.gif
barbariantuw/img/sprites/gicle3.gif
barbariantuw/img/sprites/gnome1.gif
barbariantuw/img/sprites/gnome2.gif
barbariantuw/img/sprites/gnome3.gif
barbariantuw/img/sprites/gnome4.gif
barbariantuw/img/sprites/marianna.gif
barbariantuw/img/sprites/sang.gif
barbariantuw/img/spritesA/assis1.gif
barbariantuw/img/spritesA/assis2.gif
barbariantuw/img/spritesA/attente1.gif
barbariantuw/img/spritesA/attente2.gif
barbariantuw/img/spritesA/attente3.gif
barbariantuw/img/spritesA/cou2.gif
barbariantuw/img/spritesA/cou3.gif
barbariantuw/img/spritesA/debout.gif
barbariantuw/img/spritesA/decap1.gif
barbariantuw/img/spritesA/decap2.gif
barbariantuw/img/spritesA/decap3.gif
barbariantuw/img/spritesA/decap4.gif
barbariantuw/img/spritesA/devant1.gif
barbariantuw/img/spritesA/devant2.gif
barbariantuw/img/spritesA/devant3.gif
barbariantuw/img/spritesA/front1.gif
barbariantuw/img/spritesA/front2.gif
barbariantuw/img/spritesA/front3.gif
barbariantuw/img/spritesA/genou1.gif
barbariantuw/img/spritesA/genou3.gif
barbariantuw/img/spritesA/marche1.gif
barbariantuw/img/spritesA/marche2.gif
barbariantuw/img/spritesA/marche3.gif
barbariantuw/img/spritesA/mort2.gif
barbariantuw-1.0.0.dist-info/licenses/LICENSE
barbariantuw-1.0.0.dist-info/METADATA
barbariantuw-1.0.0.dist-info/WHEEL
barbariantuw-1.0.0.dist-info/entry_points.txt
barbariantuw-1.0.0.dist-info/top_level.txt
barbariantuw-1.0.0.dist-info/RECORD
