Metadata-Version: 2.4
Name: barbariantuw
Version: 1.0.0
Summary: 'Barbarian - The Ultimate Warrior' game remake
Author: Cthulhu Fhtagn
License-Expression: MIT
Project-URL: Homepage, https://codeberg.org/cthulhu/barbarian
Project-URL: Issues, https://codeberg.org/cthulhu/barbarian/issues
Classifier: Programming Language :: Python :: 3
Classifier: Operating System :: OS Independent
Classifier: Topic :: Games/Entertainment
Classifier: Topic :: Games/Entertainment :: Arcade
Requires-Python: >=3.10
License-File: LICENSE
Requires-Dist: pygame-ce
Provides-Extra: nuitka
Requires-Dist: psutil; extra == "nuitka"
Requires-Dist: nuitka; extra == "nuitka"
Provides-Extra: dev
Requires-Dist: psutil; extra == "dev"
Requires-Dist: build; extra == "dev"
Requires-Dist: pygbag; extra == "dev"
Requires-Dist: memray; extra == "dev"
Requires-Dist: snakeviz; extra == "dev"
Dynamic: license-file
